genai_scaffold/__init__.py
genai_scaffold/__main__.py
genai_scaffold/scaffold.py
genai_scaffold/template_structure.py
genai_scaffold-0.1.4.1.dist-info/licenses/LICENSE
genai_scaffold-0.1.4.1.dist-info/METADATA
genai_scaffold-0.1.4.1.dist-info/WHEEL
genai_scaffold-0.1.4.1.dist-info/entry_points.txt
genai_scaffold-0.1.4.1.dist-info/top_level.txt
genai_scaffold-0.1.4.1.dist-info/RECORD
