Metadata-Version: 2.4
Name: genai-scaffold
Version: 0.1.4.1
Summary: CLI tool to scaffold production-ready Generative AI projects
Author-email: Akinyemi Arabambi <yemiarabambi@gmail.com>
License-Expression: MIT
Project-URL: Repository, https://github.com/2abet/genai_scaffold
Requires-Python: >=3.8
License-File: LICENSE
Dynamic: license-file
